{
  "generated_at": "2026-07-23T00:00:00Z",
  "project_root": "/Users/iagoleal/dev/aps-inteligente",
  "re_extraction": 2,
  "languages": [
    { "name": "TypeScript", "extensions": [".ts", ".tsx"], "file_count": 97 },
    { "name": "CSS", "extensions": [".css"], "file_count": 6 },
    { "name": "JavaScript", "extensions": [".js", ".mjs"], "file_count": 4 }
  ],
  "primary_language": "TypeScript",
  "frameworks": [
    { "name": "Next.js", "version": "16.2.10", "source": "package.json", "note": "Pages Router, Turbopack" },
    { "name": "React", "version": "19.2.4", "source": "package.json" },
    { "name": "@primer/react", "version": "38.33.0", "source": "package.json", "note": "sistema de design GitHub Primer (feature 004+)" },
    { "name": "@primer/octicons-react", "version": "19.29.2", "source": "package.json" },
    { "name": "pg", "version": "8.22.0", "source": "package.json", "note": "driver PostgreSQL — so healthcheck de status (feature 003)" },
    { "name": "Vitest", "version": "4.1.10", "source": "package.json", "note": "unidade + integracao + contrato" },
    { "name": "Playwright", "version": "1.61.1", "source": "package.json", "note": "e2e + axe-core acessibilidade" },
    { "name": "fast-check", "version": "4.9.0", "source": "package.json", "note": "property-based testing do dominio" }
  ],
  "package_manager": "npm",
  "entry_points": [
    { "path": "pages/index.tsx", "type": "app_entry", "note": "home por secoes (feature 007)" },
    { "path": "pages/_app.tsx", "type": "app_shell", "note": "importa globais.css, inicio.css, cabecalho.css, cardiologia.css" },
    { "path": "pages/_document.tsx", "type": "document", "note": "links de icone/manifest/theme-color, PWA (feature 009)" },
    { "path": "pages/dm2/insulina.tsx", "type": "page_route" },
    { "path": "pages/pre-natal/idade-gestacional.tsx", "type": "page_route" },
    { "path": "pages/cardiologia/dor-toracica.tsx", "type": "page_route" },
    { "path": "pages/api/v1/status.ts", "type": "api_route", "note": "GET /api/v1/status — contrato fixo (feature 002)" }
  ],
  "config_files": [
    "next.config.ts", "tsconfig.json", "vercel.json", "eslint.config.mjs",
    "vitest.config.ts", "vitest.api.config.ts", "playwright.config.ts",
    ".env.example", "infra/compose.yaml"
  ],
  "ci_cd": [
    ".github/workflows/ci.yml"
  ],
  "docker": {
    "compose": "infra/compose.yaml"
  },
  "database_hints": [
    { "path": "infra/database.ts", "type": "pg_pool_singleton", "note": "pool pg lazy; usado so pelo healthcheck de status" },
    { "path": "infra/compose.yaml", "type": "compose_service", "note": "postgres:17.10-alpine local; producao via integracao Neon (Vercel Marketplace)" }
  ],
  "test_framework": "Vitest + Playwright",
  "test_file_count": 33,
  "modules": [
    "models/insulina",
    "models/gestacao",
    "models/cardiopatia-isquemica",
    "interface/calculadora",
    "interface/cardiologia",
    "interface/gestacao",
    "interface/inicio",
    "interface/comum",
    "interface/estilos",
    "pages",
    "pages/api/v1/status",
    "infra"
  ],
  "total_files": 107,
  "organization_suggestion": {
    "granularity": "module",
    "rationale": "Pastas top-level por dominio em models/ (insulina, gestacao, cardiopatia-isquemica) e interface/ espelhadas em pages/ por rota; organizacao por modulo ja persistida em config.toml.",
    "signals": [
      { "type": "top_level_domain_folders", "evidence": ["models/insulina/", "models/gestacao/", "models/cardiopatia-isquemica/", "interface/calculadora/", "interface/cardiologia/", "interface/gestacao/"] },
      { "type": "route_folders", "evidence": ["pages/dm2/insulina.tsx", "pages/pre-natal/idade-gestacional.tsx", "pages/cardiologia/dor-toracica.tsx"] }
    ],
    "features": []
  }
}
